instutil/__init__.py
instutil/inst_util.py
instutil-0.2.4.dist-info/licenses/LICENSE
instutil-0.2.4.dist-info/METADATA
instutil-0.2.4.dist-info/WHEEL
instutil-0.2.4.dist-info/top_level.txt
instutil-0.2.4.dist-info/RECORD
