Metadata-Version: 2.4
Name: instutil
Version: 0.2.4
Summary: tools for data processing and tcp communications
Author-email: Carl Wilson <cawilson@vitro.com>
License-Expression: MIT
Classifier: Programming Language :: Python :: 3
Classifier: Operating System :: Microsoft :: Windows :: Windows 10
Requires-Python: >=3.11
License-File: LICENSE
Dynamic: license-file
